dockershrink/__init__.py
dockershrink/ai.py
dockershrink/cli.py
dockershrink/dockerignore.py
dockershrink/package_json.py
dockershrink/dockerfile/__init__.py
dockershrink/dockerfile/ast.py
dockershrink/dockerfile/dockerfile.py
dockershrink/dockerfile/image.py
dockershrink/dockerfile/layer.py
dockershrink/dockerfile/shell_command.py
dockershrink/dockerfile/stage.py
dockershrink/project/__init__.py
dockershrink/project/helpers.py
dockershrink/project/optimization_action.py
dockershrink/project/project.py
dockershrink/utils/__init__.py
dockershrink/utils/log.py
dockershrink_jana-0.1.5.dist-info/LICENSE
dockershrink_jana-0.1.5.dist-info/METADATA
dockershrink_jana-0.1.5.dist-info/WHEEL
dockershrink_jana-0.1.5.dist-info/entry_points.txt
dockershrink_jana-0.1.5.dist-info/top_level.txt
dockershrink_jana-0.1.5.dist-info/RECORD
